{
  "content": [
    {
      "content": null,
      "created": "2022-12-01T15:54:58.051314Z",
      "format": null,
      "last_modified": "2022-12-01T15:54:54.267305Z",
      "mimetype": "image/png",
      "name": "schematic-lasing-model.png",
      "path": "tutorials/lectures/images/schematic-lasing-model.png",
      "size": 23024,
      "type": "file",
      "writable": true
    },
    {
      "content": null,
      "created": "2022-12-01T15:54:58.047314Z",
      "format": null,
      "last_modified": "2022-12-01T15:54:54.267305Z",
      "mimetype": "image/png",
      "name": "qobj.png",
      "path": "tutorials/lectures/images/qobj.png",
      "size": 76092,
      "type": "file",
      "writable": true
    },
    {
      "content": null,
      "created": "2022-12-01T15:54:58.047314Z",
      "format": null,
      "last_modified": "2022-12-01T15:54:54.267305Z",
      "mimetype": "image/png",
      "name": "exdecay.png",
      "path": "tutorials/lectures/images/exdecay.png",
      "size": 21226,
      "type": "file",
      "writable": true
    }
  ],
  "created": "2022-12-01T15:54:58.051314Z",
  "format": "json",
  "last_modified": "2022-12-01T15:54:58.051314Z",
  "mimetype": null,
  "name": "images",
  "path": "tutorials/lectures/images",
  "size": null,
  "type": "directory",
  "writable": true
}